{
    "autos":
       [
           {"key":"sedan","value":"Sedán"},
           {"key":"camioneta-suv","value":"Camionetas SUV"},
           {"key":"hatchback","value":"Hatchback"},
           {"key":"deportivo","value":"Deportivo"},
           {"key":"pick-up","value":"Pick-Up"},
           {"key":"vans","value":"Vans","count":209},
           {"key":"station-wagon","value":"Station Wagon"},
           {"key":"otros","value":"Otros"}
       ],
    "motos":
       [
           {"key":"cross-enduro","value":"Cross Enduro"},
           {"key":"cuatrimoto","value":"Cuatrimoto"},
           {"key":"custom","value":"Custom"},
           {"key":"de-calle","value":"De calle"},
           {"key":"deportiva","value":"Deportiva"},
           {"key":"scotter","value":"Scotter"},
           {"key":"bicimoto","value":"Bicimoto"},
           {"key":"otros","value":"Otros"}
       ],
    "buses-y-camiones":
       [
           {"key":"bus","value":"Bus"},
           {"key":"camion","value":"Camión"},
           {"key":"maquinaria","value":"Maquinaria"},
           {"key":"otros","value":"Otros"}
       ]
}